<?xml version="1.0" encoding="UTF-8" standalone="no"?>
<?xml-model href="https://dplava.lib.virginia.edu/dplava.xsd" type="application/xml"
      schematypens="http://purl.oclc.org/dsdl/schematron"?><!-- Generated using uvaMAP2DPLA_no_include.xsl (v. 1.0) on 2024-06-18 at 9:08 p.m. --><mdRecord xmlns:dcterms="http://purl.org/dc/terms/"
          xmlns:edm="http://www.europeana.eu/schemas/edm/"
          xmlns:xsi="http://www.w3.org/2001/XMLSchema-instance"
          xmlns="http://dplava.lib.virginia.edu"
          xsi:schemaLocation="http://dplava.lib.virginia.edu https://dplava.lib.virginia.edu/dplava.xsd">
   <dcterms:provenance>University of Virginia</dcterms:provenance>
   <dcterms:type>text</dcterms:type>
   <dcterms:identifier>uva-lib:1143223</dcterms:identifier>
   <dcterms:title>Barcarolle: duet for mezzo-soprano and baritone (or alto), [op. 62] / poem by Éd. Guinand ; English version by Eugène Oudin ; music by C. Chaminade</dcterms:title>
   <dcterms:title>Come, for a sweet delight thrills the balmy night</dcterms:title>
   <dcterms:title>Oui, mon âme est charmée</dcterms:title>
   <dcterms:title>Chaminade, Cécile, 1857-1944. Barcarolles, voices, piano. op. 62</dcterms:title>
   <dcterms:creator>Chaminade, Cécile, 1857-1944 [original]</dcterms:creator>
   <dcterms:contributor>Guinand, Edouard [lyricist]</dcterms:contributor>
   <dcterms:contributor>Oudin, Eugène [translator]</dcterms:contributor>
   <dcterms:created>1898</dcterms:created>
   <dcterms:extent>1 score (11 p.)</dcterms:extent>
   <dcterms:medium>score [original]</dcterms:medium>
   <dcterms:description>mezzo-soprano voice, alto voice, piano [original]</dcterms:description>
   <dcterms:description>mezzo-soprano voice, baritone voice, piano [original]</dcterms:description>
   <dcterms:description>For mezzo-soprano and baritone or alto with piano. [original]</dcterms:description>
   <dcterms:description>French words with English translation. [original]</dcterms:description>
   <dcterms:description>Caption title. [original]</dcterms:description>
   <dcterms:description>Publication date derived from publisher's plate number. [original]</dcterms:description>
   <dcterms:description>Advertisement on p. [12]: New songs and duets selected from the catalogue of G. Schirmer. [original]</dcterms:description>
   <dcterms:rights>http://rightsstatements.org/vocab/CNE/1.0/</dcterms:rights>
   <dcterms:subject>Vocal duets with piano</dcterms:subject>
   <edm:preview>https://iiif.lib.virginia.edu/iiif/uva-lib:1143224/full/!125,200/0/default.jpg</edm:preview>
   <edm:isShownAt>https://search.lib.virginia.edu/sources/uva_library/items/u5314900</edm:isShownAt>
</mdRecord>