<?xml version="1.0" encoding="UTF-8" standalone="no"?>
<?xml-model href="https://dplava.lib.virginia.edu/dplava.xsd"
      type="application/xml"
      schematypens="http://purl.oclc.org/dsdl/schematron"?>
<!-- Generated using uvaMAP2DPLA.xsl (v. 1.0) on 2023-06-13 at 2:33 p.m. -->
<mdRecord xmlns="http://dplava.lib.virginia.edu"
          xmlns:dcterms="http://purl.org/dc/terms/"
          xmlns:edm="http://www.europeana.eu/schemas/edm/"
          xmlns:xsi="http://www.w3.org/2001/XMLSchema-instance"
          xsi:schemaLocation="http://dplava.lib.virginia.edu https://dplava.lib.virginia.edu/dplava.xsd">
   <dcterms:provenance>University of Virginia</dcterms:provenance>
   <dcterms:type>still image</dcterms:type>
   <dcterms:identifier>656601</dcterms:identifier>
   <dcterms:title>Houghton Hall, exterior</dcterms:title>
   <dcterms:creator>Campbell, Colen (Scottish architect and writer, 1676-ca. 1729, active in England) [work]</dcterms:creator>
   <dcterms:creator>Gibbs, James (Scottish architect, 1682-1754) [work]</dcterms:creator>
   <dcterms:creator>Kent, William (English architect, landscape gardener, and painter, 1684 or 1685-1748) [work]</dcterms:creator>
   <dcterms:creator>Ripley, Thomas (British architect, ca. 1683-1758) [work]</dcterms:creator>
   <dcterms:creator>Wilson, Richard Guy [photographer]</dcterms:creator>
   <dcterms:publisher>Rector and Visitors of the University of Virginia</dcterms:publisher>
   <dcterms:created>2003</dcterms:created>
   <dcterms:description>West facade from lawn</dcterms:description>
   <dcterms:description>Houghton Hall is a country house in Norfolk, England. It was built for the de facto first British Prime Minister, Sir Robert Walpole, and it is a key building in the history of Palladian architecture in England. Colen Campbell began the building in 1722. James Gibbs added the domes. William Kent designed the interiors. Thomas Ripley supervised the building work. http://en.wikipedia.org/wiki/Houghton_Hall [work]</dcterms:description>
   <dcterms:description>British</dcterms:description>
   <dcterms:description>Palladian</dcterms:description>
   <dcterms:isPartOf>Richard Guy Wilson Archive</dcterms:isPartOf>
   <dcterms:rights>https://creativecommons.org/licenses/by/4.0/</dcterms:rights>
   <dcterms:subject>Architecture and City Planning</dcterms:subject>
   <dcterms:subject>mansions</dcterms:subject>
   <dcterms:subject>Walpole, Robert, Earl of Orford, 1676-1745</dcterms:subject>
   <dcterms:subject>domes (architectural elements)</dcterms:subject>
   <dcterms:subject>engaged columns</dcterms:subject>
   <dcterms:subject>cornices</dcterms:subject>
   <dcterms:subject>pediments</dcterms:subject>
   <dcterms:subject>lawns (landscaped grass)</dcterms:subject>
   <dcterms:subject>Palladian windows</dcterms:subject>
   <dcterms:spatial>King's Lynn, Norfolk, England, United Kingdom</dcterms:spatial>
   <dcterms:spatial>52.8269, 0.6576</dcterms:spatial>
   <edm:preview>https://stor.artstor.org/iiif/2012/07/31/11/f5192bd9-388a-4dfe-a4ed-f1d2b94ecf4c_deflate.tif/full/!250,250/0/default.jpg</edm:preview>
   <edm:isShownAt>https://search.lib.virginia.edu/items/i_656601</edm:isShownAt>
</mdRecord>
