<?xml version="1.0" encoding="UTF-8" standalone="no"?>
<?xml-model href="https://dplava.lib.virginia.edu/dplava.xsd"
      type="application/xml"
      schematypens="http://purl.oclc.org/dsdl/schematron"?>
<!-- Generated using uvaMAP2DPLA.xsl (v. 1.0) on 2022-12-14 at 8:12 p.m. -->
<mdRecord xmlns="http://dplava.lib.virginia.edu"
          xmlns:dcterms="http://purl.org/dc/terms/"
          xmlns:edm="http://www.europeana.eu/schemas/edm/"
          xmlns:xsi="http://www.w3.org/2001/XMLSchema-instance"
          xsi:schemaLocation="http://dplava.lib.virginia.edu https://dplava.lib.virginia.edu/dplava.xsd">
   <dcterms:provenance>University of Virginia</dcterms:provenance>
   <dcterms:type>still image</dcterms:type>
   <dcterms:identifier>1085065</dcterms:identifier>
   <dcterms:title>Staatsburg Library, general view</dcterms:title>
   <dcterms:title>Saint Margaret of Antioch Church</dcterms:title>
   <dcterms:creator>Wilson, Richard Guy [photographer]</dcterms:creator>
   <dcterms:publisher>Rector and Visitors of the University of Virginia</dcterms:publisher>
   <dcterms:created>1991</dcterms:created>
   <dcterms:description>Library, exterior view</dcterms:description>
   <dcterms:description>. . . beginning in 1858, services were held in the chapel across the street, now the Staatsburg Library. That building was built by Mrs. Margaret Lewis Livingston, the mother of Mrs. Lydia Hoyt and was used by several religious groups in the village. -- http://www.stmargaretsepiscopalchurch.org/history/ [work]</dcterms:description>
   <dcterms:description>The Staatsburg Library was used as a Reading Room in 1891 and was granted its first charter by the state of New York in 1894. -- http://staatsburglibrary.org/136-2/ [work]</dcterms:description>
   <dcterms:description>American</dcterms:description>
   <dcterms:description>Carpenter Gothic</dcterms:description>
   <dcterms:isPartOf>Richard Guy Wilson Archive</dcterms:isPartOf>
   <dcterms:rights>https://creativecommons.org/licenses/by/4.0/</dcterms:rights>
   <dcterms:subject>Architecture and City Planning</dcterms:subject>
   <dcterms:subject>public libraries (buildings)</dcterms:subject>
   <dcterms:subject>adaptive reuse</dcterms:subject>
   <dcterms:subject>churches (buildings)</dcterms:subject>
   <dcterms:subject>board and batten</dcterms:subject>
   <dcterms:subject>windows</dcterms:subject>
   <dcterms:subject>porches</dcterms:subject>
   <dcterms:spatial>70 Old Post Road, Staatsburg, Dutchess, New York, United States</dcterms:spatial>
   <dcterms:spatial>41.850163, -73.927894</dcterms:spatial>
   <edm:preview>https://stor.artstor.org/iiif/2012/12/06/15/b03a02e5-be5a-41d1-9433-5b6acd59abb3_deflate.tif/full/!250,250/0/default.jpg</edm:preview>
   <edm:isShownAt>https://search.lib.virginia.edu/items/i_1085065</edm:isShownAt>
</mdRecord>
