<?xml version="1.0" encoding="UTF-8" standalone="no"?>
<?xml-model href="https://dplava.lib.virginia.edu/dplava.xsd" type="application/xml"
      schematypens="http://purl.oclc.org/dsdl/schematron"?><!-- Generated using uvaMAP2DPLA_no_include.xsl (v. 1.0) on 2024-06-18 at 9:01 p.m. --><mdRecord xmlns:dcterms="http://purl.org/dc/terms/"
          xmlns:edm="http://www.europeana.eu/schemas/edm/"
          xmlns:xsi="http://www.w3.org/2001/XMLSchema-instance"
          xmlns="http://dplava.lib.virginia.edu"
          xsi:schemaLocation="http://dplava.lib.virginia.edu https://dplava.lib.virginia.edu/dplava.xsd">
   <dcterms:provenance>University of Virginia</dcterms:provenance>
   <dcterms:type>text</dcterms:type>
   <dcterms:identifier>uva-lib:1139198</dcterms:identifier>
   <dcterms:title>A kiss, a kiss, there's nobody nigh: duetto, sung by Miss E. Jefferson and Mr. Hutchins in the operatic comedy of The rencontre at the Philadelphia Theatre / composed by Henry R. Bishop ; the poetry by J.R. Planche ; arranged by H. Willis</dcterms:title>
   <dcterms:title>A kiss, a kiss, there's nobody nigh</dcterms:title>
   <dcterms:title>Bishop, Henry R. (Henry Rowley), 1786-1855. Rencontre. Kiss, a kiss, there's nobody nigh</dcterms:title>
   <dcterms:creator>Bishop, Henry R. (Henry Rowley), 1786-1855 [original]</dcterms:creator>
   <dcterms:contributor>Hutchins Mr [performer]</dcterms:contributor>
   <dcterms:contributor>Jefferson, E. [performer]</dcterms:contributor>
   <dcterms:contributor>Planché, J. R. (James Robinson), 1796-1880 [original]</dcterms:contributor>
   <dcterms:contributor>Willis, H. [arranger]</dcterms:contributor>
   <dcterms:created>[1840..1853]</dcterms:created>
   <dcterms:extent>1 vocal score (4 p.)</dcterms:extent>
   <dcterms:medium>score [original]</dcterms:medium>
   <dcterms:description>voice (2), piano [original]</dcterms:description>
   <dcterms:description>For 2 voices and piano. [original]</dcterms:description>
   <dcterms:description>Publication date derived from publisher's address. Cf. Handbook of early American sheet music / Dichter and Shapiro. [original]</dcterms:description>
   <dcterms:rights>http://rightsstatements.org/vocab/CNE/1.0/</dcterms:rights>
   <dcterms:subject>Operas--Excerpts--Vocal scores with piano</dcterms:subject>
   <dcterms:subject>Vocal duets with piano</dcterms:subject>
   <edm:preview>https://iiif.lib.virginia.edu/iiif/uva-lib:1139199/full/!125,200/0/default.jpg</edm:preview>
   <edm:isShownAt>https://search.lib.virginia.edu/sources/uva_library/items/u5314610</edm:isShownAt>
</mdRecord>