<?xml version="1.0" encoding="UTF-8" standalone="no"?>
<?xml-model href="https://dplava.lib.virginia.edu/dplava.xsd"
      type="application/xml"
      schematypens="http://purl.oclc.org/dsdl/schematron"?>
<!-- Generated using uvaMAP2DPLA.xsl (v. 1.0) on 2023-06-13 at 11:52 a.m. -->
<mdRecord xmlns="http://dplava.lib.virginia.edu"
          xmlns:dcterms="http://purl.org/dc/terms/"
          xmlns:edm="http://www.europeana.eu/schemas/edm/"
          xmlns:xsi="http://www.w3.org/2001/XMLSchema-instance"
          xsi:schemaLocation="http://dplava.lib.virginia.edu https://dplava.lib.virginia.edu/dplava.xsd">
   <dcterms:provenance>University of Virginia</dcterms:provenance>
   <dcterms:type>still image</dcterms:type>
   <dcterms:identifier>16237327</dcterms:identifier>
   <dcterms:title>Corsham Court, exterior|general view</dcterms:title>
   <dcterms:creator>Bellamy, Thomas (British architect, 19th century) [additions]</dcterms:creator>
   <dcterms:creator>Brown, Capability (English landscape architect, 1716-1783) [to redesign and enlarge the house and landscape the park]</dcterms:creator>
   <dcterms:creator>Keene, Henry (British architect, 1726-1776) [additions]</dcterms:creator>
   <dcterms:creator>Repton, Humphry (English landscape architect and writer, 1752-1818) [garden completion]</dcterms:creator>
   <dcterms:creator>Wilson, Richard Guy [photographer]</dcterms:creator>
   <dcterms:publisher>Rector and Visitors of the University of Virginia</dcterms:publisher>
   <dcterms:created>2003</dcterms:created>
   <dcterms:description>Entrance facade</dcterms:description>
   <dcterms:description>Begun in 1582 by Thomas Smythe; bought by the Methuen family in 1745. Additions made prior to 1749; in 1759 Henry Keene provided plans for additions which were carried out by L. Brown in 1761. In 1800 John Nash enlarged the house; in 1845 Bellamy removed Nash's work on the north front, adding the present structure. Brown began the gardens in 1761; completed by H. Repton in 1799. -- Pevsner and Cherry, Wiltshire, 1976 [work]</dcterms:description>
   <dcterms:description>British</dcterms:description>
   <dcterms:description>English</dcterms:description>
   <dcterms:description>Tudor</dcterms:description>
   <dcterms:description>Jacobean Revival</dcterms:description>
   <dcterms:isPartOf>Richard Guy Wilson Archive</dcterms:isPartOf>
   <dcterms:rights>https://creativecommons.org/licenses/by/4.0/</dcterms:rights>
   <dcterms:subject>Architecture and City Planning</dcterms:subject>
   <dcterms:subject>Garden and Landscape</dcterms:subject>
   <dcterms:subject>dwellings</dcterms:subject>
   <dcterms:subject>landscape gardening</dcterms:subject>
   <dcterms:subject>Nash, John (English architect and town planner, 1752-1835)</dcterms:subject>
   <dcterms:subject>façades</dcterms:subject>
   <dcterms:subject>driveways</dcterms:subject>
   <dcterms:spatial>Church St, Corsham SN13 0BY, UK, Church St, Corsham, Wiltshire, England, United Kingdom</dcterms:spatial>
   <dcterms:spatial>51.435, -2.1825</dcterms:spatial>
   <edm:preview>https://stor.artstor.org/iiif/2016/08/01/16/bd1f5d76-6d89-4710-8c88-0e7b288b1a4f_deflate.tif/full/!250,250/0/default.jpg</edm:preview>
   <edm:isShownAt>https://search.lib.virginia.edu/items/i_16237327</edm:isShownAt>
</mdRecord>
