<?xml version="1.0" encoding="UTF-8" standalone="no"?>
<?xml-model href="https://dplava.lib.virginia.edu/dplava.xsd" type="application/xml"
      schematypens="http://purl.oclc.org/dsdl/schematron"?><!-- Generated using uvaMAP2DPLA_no_include.xsl (v. 1.0) on 2024-06-18 at 8:38 p.m. --><mdRecord xmlns:dcterms="http://purl.org/dc/terms/"
          xmlns:edm="http://www.europeana.eu/schemas/edm/"
          xmlns:xsi="http://www.w3.org/2001/XMLSchema-instance"
          xmlns="http://dplava.lib.virginia.edu"
          xsi:schemaLocation="http://dplava.lib.virginia.edu https://dplava.lib.virginia.edu/dplava.xsd">
   <dcterms:provenance>University of Virginia</dcterms:provenance>
   <dcterms:type>text</dcterms:type>
   <dcterms:identifier>uva-lib:1124060</dcterms:identifier>
   <dcterms:title>Strauss' Engagement waltzes / [Johann Strauss]</dcterms:title>
   <dcterms:title>Engagement waltzes</dcterms:title>
   <dcterms:creator>Strauss, Johann, 1825-1899 [original]</dcterms:creator>
   <dcterms:contributor>Davenport Bros [engraver]</dcterms:contributor>
   <dcterms:created>1873</dcterms:created>
   <dcterms:extent>11 p. of music.</dcterms:extent>
   <dcterms:description>piano [original]</dcterms:description>
   <dcterms:description>For piano solo; originally for orchestra. [original]</dcterms:description>
   <dcterms:description>Caption title. [original]</dcterms:description>
   <dcterms:description>Attributed to Strauss. Cf. Grove music online. [original]</dcterms:description>
   <dcterms:description>"Davenport Bros., eng. &amp; print., Boston"--Colophon. [original]</dcterms:description>
   <dcterms:description>Advertisement on p. [12]: Goullaud's popular sheet music. [original]</dcterms:description>
   <dcterms:rights>http://rightsstatements.org/vocab/CNE/1.0/</dcterms:rights>
   <dcterms:subject>Piano music, Arranged</dcterms:subject>
   <dcterms:subject>Waltzes</dcterms:subject>
   <dcterms:subject>Popular instrumental music--To 1901</dcterms:subject>
   <dcterms:temporal>To 1901</dcterms:temporal>
   <edm:preview>https://iiif.lib.virginia.edu/iiif/uva-lib:1124061/full/!125,200/0/default.jpg</edm:preview>
   <edm:isShownAt>https://search.lib.virginia.edu/sources/uva_library/items/u5313676</edm:isShownAt>
</mdRecord>