<?xml version="1.0" encoding="UTF-8" standalone="no"?>
<?xml-model href="https://dplava.lib.virginia.edu/dplava.xsd" type="application/xml"
      schematypens="http://purl.oclc.org/dsdl/schematron"?>
<!-- Generated using uvaMAP2DPLA.xsl (v. 1.0) on 2023-10-26 at 12:40 p.m. -->
<mdRecord xmlns="http://dplava.lib.virginia.edu"
          xmlns:dcterms="http://purl.org/dc/terms/"
          xmlns:edm="http://www.europeana.eu/schemas/edm/"
          xmlns:xsi="http://www.w3.org/2001/XMLSchema-instance"
          xsi:schemaLocation="http://dplava.lib.virginia.edu https://dplava.lib.virginia.edu/dplava.xsd">
   <dcterms:provenance>University of Virginia</dcterms:provenance>
   <dcterms:type>text</dcterms:type>
   <dcterms:identifier>u4487</dcterms:identifier>
   <dcterms:title>Letters of instruction to surgeons and assistant surgeons of hospitals and others in charge of the money and other effects of deceased officers and soldiers: with the laws, regulations, and others relating thereto / Richmond, August 1, 1864</dcterms:title>
   <dcterms:contributor>Confederate States of America. Department of the Treasury. Second Auditor's Office.</dcterms:contributor>
   <dcterms:contributor>Confederate States of America. War Department.</dcterms:contributor>
   <dcterms:created>1864</dcterms:created>
   <dcterms:extent>3 unnumbered pages</dcterms:extent>
   <dcterms:extent>28 cm</dcterms:extent>
   <dcterms:language>English</dcterms:language>
   <dcterms:description>W.H.S. Taylor, Second Auditor Confederate States.</dcterms:description>
   <dcterms:description>Contains War Dept. General orders nos. 80, 49, 67, 68 and 1 Oct. 1862--Jan. 1864.</dcterms:description>
   <dcterms:description>Accompanied by ms list of the effects of several soldiers made pursuant to the orders.</dcterms:description>
   <dcterms:description>SPECIAL COLLECTIONS: One folded leaf from a logbook listing deceased soldiers and their effects, which was laid in, has been transferred to MSS 12511.</dcterms:description>
   <dcterms:rights>http://rightsstatements.org/vocab/CNE/1.0/</dcterms:rights>
   <dcterms:subject>Personal belongings--Confederate States of America</dcterms:subject>
   <dcterms:spatial>Confederate States of America</dcterms:spatial>
   <dcterms:spatial>Southern States</dcterms:spatial>
   <edm:preview>https://iiif.lib.virginia.edu/iiif/uva-lib:2184298/full/!125,200/0/default.jpg</edm:preview>
   <edm:isShownAt>https://search.lib.virginia.edu/sources/uva_library/items/u4487</edm:isShownAt>
</mdRecord>
