<?xml version="1.0" encoding="UTF-8" standalone="no"?>
<?xml-model href="https://dplava.lib.virginia.edu/dplava.xsd" type="application/xml"
      schematypens="http://purl.oclc.org/dsdl/schematron"?><!-- Generated using uvaMAP2DPLA_no_include.xsl (v. 1.0) on 2024-06-18 at 9:07 p.m. --><mdRecord xmlns:dcterms="http://purl.org/dc/terms/"
          xmlns:edm="http://www.europeana.eu/schemas/edm/"
          xmlns:xsi="http://www.w3.org/2001/XMLSchema-instance"
          xmlns="http://dplava.lib.virginia.edu"
          xsi:schemaLocation="http://dplava.lib.virginia.edu https://dplava.lib.virginia.edu/dplava.xsd">
   <dcterms:provenance>University of Virginia</dcterms:provenance>
   <dcterms:type>text</dcterms:type>
   <dcterms:identifier>uva-lib:1142765</dcterms:identifier>
   <dcterms:title>The friar of orders grey / by Shield</dcterms:title>
   <dcterms:title>I am a friar of orders grey</dcterms:title>
   <dcterms:title>Reeve, William, 1757-1815. Merry Sherwood. I am a friar of orders grey</dcterms:title>
   <dcterms:creator>Reeve, William, 1757-1815 [original]</dcterms:creator>
   <dcterms:contributor>Shield, William, 1748-1829 [original]</dcterms:contributor>
   <dcterms:created>[1873..1890]</dcterms:created>
   <dcterms:extent>1 score (5 p.)</dcterms:extent>
   <dcterms:medium>score [original]</dcterms:medium>
   <dcterms:description>piano, voice [original]</dcterms:description>
   <dcterms:description>For voice and piano. [original]</dcterms:description>
   <dcterms:description>Caption title. [original]</dcterms:description>
   <dcterms:description>Advertisement on p. [6]: Gordon's enlarged and improved edition of Richardson's Instructions for the piano forte. [original]</dcterms:description>
   <dcterms:description>Publisher name and address derived from advertisement. [original]</dcterms:description>
   <dcterms:description>Publication date derived from publisher's address. Cf. Handbook of early American sheet music / Dichter and Shapiro. [original]</dcterms:description>
   <dcterms:rights>http://rightsstatements.org/vocab/CNE/1.0/</dcterms:rights>
   <dcterms:subject>Songs with piano</dcterms:subject>
   <dcterms:subject>Friars--Songs and music</dcterms:subject>
   <dcterms:subject>Popular music--United States--To 1901</dcterms:subject>
   <dcterms:temporal>To 1901</dcterms:temporal>
   <dcterms:spatial>United States</dcterms:spatial>
   <edm:preview>https://iiif.lib.virginia.edu/iiif/uva-lib:1142766/full/!125,200/0/default.jpg</edm:preview>
   <edm:isShownAt>https://search.lib.virginia.edu/sources/uva_library/items/u5314878</edm:isShownAt>
</mdRecord>