<?xml version="1.0" encoding="UTF-8" standalone="no"?>
<?xml-model href="https://dplava.lib.virginia.edu/dplava.xsd"
      type="application/xml"
      schematypens="http://purl.oclc.org/dsdl/schematron"?>
<!-- Generated using uvaMAP2DPLA.xsl (v. 1.0) on 2022-12-15 at 7:49 p.m. -->
<mdRecord xmlns="http://dplava.lib.virginia.edu"
          xmlns:dcterms="http://purl.org/dc/terms/"
          xmlns:edm="http://www.europeana.eu/schemas/edm/"
          xmlns:xsi="http://www.w3.org/2001/XMLSchema-instance"
          xsi:schemaLocation="http://dplava.lib.virginia.edu https://dplava.lib.virginia.edu/dplava.xsd">
   <dcterms:provenance>University of Virginia</dcterms:provenance>
   <dcterms:type>still image</dcterms:type>
   <dcterms:identifier>33007151</dcterms:identifier>
   <dcterms:title>Beta Bridge painted for Mrs. Evelyn Turnbull's birthday: Mrs. Turnbull stands with Murray Howard in front of the bridge</dcterms:title>
   <dcterms:publisher>Rector and Visitors of the University of Virginia</dcterms:publisher>
   <dcterms:created>1986-08</dcterms:created>
   <dcterms:description>American</dcterms:description>
   <dcterms:isPartOf>James Murray Howard University of Virginia Historic Buildings and Grounds Collection</dcterms:isPartOf>
   <dcterms:rights>http://rightsstatements.org/vocab/InC/1.0/</dcterms:rights>
   <dcterms:subject>Photographs</dcterms:subject>
   <dcterms:subject>bridges (built works)</dcterms:subject>
   <dcterms:subject>birthdays</dcterms:subject>
   <dcterms:subject>signs (declaratory or advertising artifacts)</dcterms:subject>
   <dcterms:subject>Howard, James Murray (American architect and university professor, 1947-2007)</dcterms:subject>
   <edm:preview>https://stor.artstor.org/iiif/2022/07/13/16/0d357840-4f0d-4f5c-bb51-7de7b61f3c51_deflate.tif/full/!250,250/0/default.jpg</edm:preview>
   <edm:isShownAt>https://search.lib.virginia.edu/items/i_33007151</edm:isShownAt>
</mdRecord>
