<?xml version="1.0" encoding="UTF-8" standalone="no"?>
<?xml-model href="https://dplava.lib.virginia.edu/dplava.xsd"
      type="application/xml"
      schematypens="http://purl.oclc.org/dsdl/schematron"?>
<!-- Generated using uvaMAP2DPLA.xsl (v. 1.0) on 2022-12-15 at 7:43 p.m. -->
<mdRecord xmlns="http://dplava.lib.virginia.edu"
          xmlns:dcterms="http://purl.org/dc/terms/"
          xmlns:edm="http://www.europeana.eu/schemas/edm/"
          xmlns:xsi="http://www.w3.org/2001/XMLSchema-instance"
          xsi:schemaLocation="http://dplava.lib.virginia.edu https://dplava.lib.virginia.edu/dplava.xsd">
   <dcterms:provenance>University of Virginia</dcterms:provenance>
   <dcterms:type>still image</dcterms:type>
   <dcterms:identifier>28703486</dcterms:identifier>
   <dcterms:title>Piedmont, exterior|general view</dcterms:title>
   <dcterms:creator>Maury, Reuben (American farmer and carpenter, 1785-1869) [builder]</dcterms:creator>
   <dcterms:publisher>Rector and Visitors of the University of Virginia</dcterms:publisher>
   <dcterms:created>[1800..1938]</dcterms:created>
   <dcterms:description>Side with view of icehouse and 1959 faculty housing</dcterms:description>
   <dcterms:description>Piedmont was the nineteenth-century seat of the Maury family. The south wing of the present house is the earliest component and may have been constructed about 1806 by Reuben Maury, a carpenter. Wings and other additions ca. 1830-ca. 1860 and 1938. The property originally included the present house, its adjoining outbuilding, a barn and a cemetery. The University acquired the property in 1942. -- UVa Office of the Architect Report [work]</dcterms:description>
   <dcterms:description>American</dcterms:description>
   <dcterms:isPartOf>James Murray Howard University of Virginia Historic Buildings and Grounds Collection</dcterms:isPartOf>
   <dcterms:rights>http://rightsstatements.org/vocab/InC/1.0/</dcterms:rights>
   <dcterms:subject>Architecture and City Planning</dcterms:subject>
   <dcterms:subject>dwellings</dcterms:subject>
   <dcterms:subject>houses</dcterms:subject>
   <dcterms:subject>farmhouses</dcterms:subject>
   <dcterms:subject>icehouses</dcterms:subject>
   <dcterms:spatial>121 Mimosa Drive, Charlottesville, Virginia, United States</dcterms:spatial>
   <edm:preview>https://stor.artstor.org/iiif/2020/08/26/12/e4051747-38e8-40f8-b770-54b72b4198c4_deflate.tif/full/!250,250/0/default.jpg</edm:preview>
   <edm:isShownAt>https://search.lib.virginia.edu/items/i_28703486</edm:isShownAt>
</mdRecord>
