<?xml version="1.0" encoding="UTF-8" standalone="no"?>
<?xml-model href="https://dplava.lib.virginia.edu/dplava.xsd" type="application/xml" schematypens="http://purl.oclc.org/dsdl/schematron"?><!-- Generated using uvaMAP2DPLA_no_include.xsl (v. 1.0) on 2021-11-23 at 3:45 a.m. --><mdRecord xmlns:dcterms="http://purl.org/dc/terms/"
          xmlns:edm="http://www.europeana.eu/schemas/edm/"
          xmlns:xsi="http://www.w3.org/2001/XMLSchema-instance"
          xmlns="http://dplava.lib.virginia.edu"
          xsi:schemaLocation="http://dplava.lib.virginia.edu https://dplava.lib.virginia.edu/dplava.xsd">
   <dcterms:provenance>University of Virginia</dcterms:provenance>
   <dcterms:type>text</dcterms:type>
   <dcterms:identifier>uva-lib:1120891</dcterms:identifier>
   <dcterms:title>See thee and forget thee never / as sung with immense success in Erminie by Henry Hallam</dcterms:title>
   <dcterms:title>See thee and forget thee, no</dcterms:title>
   <dcterms:title>Jakobowski, Edward, 1858-1927. Erminie. See thee and forget thee never.</dcterms:title>
   <dcterms:creator>Jakobowski, Edward, 1858-1927</dcterms:creator>
   <dcterms:publisher>Richard A. Saalfield</dcterms:publisher>
   <dcterms:created>189X</dcterms:created>
   <dcterms:extent>1 vocal score (5 p.)</dcterms:extent>
   <dcterms:medium>piano score</dcterms:medium>
   <dcterms:language>English</dcterms:language>
   <dcterms:description>piano, voice</dcterms:description>
   <dcterms:description>For voice and piano.</dcterms:description>
   <dcterms:description>Composed by Edward Jakobowski; first performed in 1890.</dcterms:description>
   <dcterms:rights>http://rightsstatements.org/vocab/NoC-US/1.0/</dcterms:rights>
   <dcterms:subject>Songs with piano</dcterms:subject>
   <dcterms:subject>Musicals--Excerpts--Vocal scores with piano.</dcterms:subject>
   <dcterms:subject>Popular music--United States--To 1901.</dcterms:subject>
   <dcterms:temporal>To 1901.</dcterms:temporal>
   <dcterms:spatial>United States</dcterms:spatial>
   <edm:preview>https://iiif.lib.virginia.edu/iiif/uva-lib:1120892/full/!125,200/0/default.jpg</edm:preview>
   <edm:isShownAt>http://search.lib.virginia.edu/catalog/uva-lib:1120891</edm:isShownAt>
</mdRecord>